QuickAES/__init__.py
QuickAES-1.0.2.dist-info/METADATA
QuickAES-1.0.2.dist-info/WHEEL
QuickAES-1.0.2.dist-info/top_level.txt
QuickAES-1.0.2.dist-info/RECORD
