Metadata-Version: 2.1
Name: QuickAES
Version: 1.0.2
Summary: Quick Encrypt and Decrypt Text
Home-page: 
Author: CarbonBlackz
Author-email: carbonblack.ns@gmail.com
License: MIT
Keywords: encrypt
Classifier: Development Status :: 5 - Production/Stable
Classifier: Intended Audience :: Education
Classifier: Operating System :: Microsoft :: Windows :: Windows 10
Classifier: License :: OSI Approved :: MIT License
Classifier: Programming Language :: Python :: 3
Requires-Dist: pycryptodome
